<?xml version="1.0" encoding="UTF-8"?>
<metadata>
  <identifier>WARCdealer_BarrelData_rochuwd_1134a985-1c1f-48e6-97a2-ddc768dfe9e5.2016-03-17-10-53-45-622575-_E</identifier>
  <publicdate>2016-03-17 09:53:57</publicdate>
  <title>WARCdealer_BarrelData_rochuwd_1134a985-1c1f-48e6-97a2-ddc768dfe9e5.2016-03-17-10-53-45-622575-_E</title>
  <mediatype>data</mediatype>
  <collection>opensource</collection>
  <uploader>worldpeacehaven@gmail.com</uploader>
  <addeddate>2016-03-17 09:53:57</addeddate>
  <curation>[curator]validator@archive.org[/curator][date]20160317095420[/date][comment]checked for malware[/comment]</curation>
</metadata>
