<?xml version="1.0" encoding="UTF-8"?>
<metadata>
  <identifier>AMVRWBYRedYellow6PfGNEhZf8</identifier>
  <collection>opensource_movies</collection>
  <description>I do not own the song of this video all rights go to roosterteeth&lt;br /&gt;&lt;br /&gt;AMV RWBY&lt;br /&gt;&lt;br /&gt;Can I get 5 likes?</description>
  <mediatype>movies</mediatype>
  <scanner>Internet Archive Python library 0.8.1</scanner>
  <subject>UCcuPkV6iSGetO7KJJ-VLrsg</subject>
  <title>AMV RWBY (Red &amp; Yellow)</title>
  <subject>Youtube rip by ET3RN4L</subject>
  <subject>AMV</subject>
  <subject>RWBY</subject>
  <subject>(Red</subject>
  <subject>&amp;</subject>
  <subject>Yellow)</subject>
  <subject>6PfGN_EhZf8</subject>
  <publicdate>2015-05-03 05:15:10</publicdate>
  <uploader>worldpeacehaven@gmail.com</uploader>
  <addeddate>2015-05-03 05:15:10</addeddate>
  <curation>[curator]validator@archive.org[/curator][date]20150503051532[/date][comment]checked for malware[/comment]</curation>
</metadata>
