<?xml version="1.0" encoding="UTF-8"?>
<metadata>
  <identifier>AMJ_BarrelData_7228_1cce1746-1eae-4ba5-a24a-d7a4b85b74ea.2013-12-28-00-16-11-581287-_E</identifier>
  <collection>amjbarreldata</collection>
  <description>Arcmaj3 data. Barrel 7228, 1cce1746-1eae-4ba5-a24a-d7a4b85b74ea</description>
  <mediatype>web</mediatype>
  <subject>Arcmaj3; WARC; snapshot; archive; Arcmaj3BarrelData</subject>
  <title>Arcmaj3 data. Barrel 7228, 1cce1746-1eae-4ba5-a24a-d7a4b85b74ea</title>
  <publicdate>2013-12-28 05:23:46</publicdate>
  <uploader>worldpeacehaven@gmail.com</uploader>
  <addeddate>2013-12-28 05:23:46</addeddate>
  <curation>[curator]malware@archive.org[/curator][date]20140313192710[/date][comment]checked for malware[/comment]</curation>
  <collection>data</collection>
</metadata>
