<?xml version="1.0" encoding="UTF-8"?>
<metadata>
  <identifier>AMJ_BarrelData_4508_98aedb83-f298-4bd7-b19b-d92fadcf50b3.2013-11-26-01-15-43-793567-_E</identifier>
  <collection>amjbarreldata</collection>
  <description>Arcmaj3 data. Barrel 4508, 98aedb83-f298-4bd7-b19b-d92fadcf50b3</description>
  <mediatype>web</mediatype>
  <subject>Arcmaj3; WARC; snapshot; archive; Arcmaj3BarrelData</subject>
  <title>Arcmaj3 data. Barrel 4508, 98aedb83-f298-4bd7-b19b-d92fadcf50b3</title>
  <publicdate>2013-11-26 06:17:48</publicdate>
  <uploader>worldpeacehaven@gmail.com</uploader>
  <addeddate>2013-11-26 06:17:48</addeddate>
  <curation>[curator]malware@archive.org[/curator][date]20140314033452[/date][comment]checked for malware[/comment]</curation>
  <collection>data</collection>
  <backup_location>ia905800_14</backup_location>
</metadata>
