<?xml version="1.0" encoding="UTF-8"?>
<metadata>
  <identifier>AMJ_BarrelData_5260_fc3a0f8e-8be0-40cf-92e2-5b9c3988133f.2013-11-26-05-36-42-229299-_E</identifier>
  <collection>amjbarreldata</collection>
  <description>Arcmaj3 data. Barrel 5260, fc3a0f8e-8be0-40cf-92e2-5b9c3988133f</description>
  <mediatype>web</mediatype>
  <subject>Arcmaj3; WARC; snapshot; archive; Arcmaj3BarrelData</subject>
  <title>Arcmaj3 data. Barrel 5260, fc3a0f8e-8be0-40cf-92e2-5b9c3988133f</title>
  <publicdate>2013-11-26 10:40:25</publicdate>
  <uploader>worldpeacehaven@gmail.com</uploader>
  <addeddate>2013-11-26 10:40:25</addeddate>
  <curation>[curator]malware@archive.org[/curator][date]20140314032522[/date][comment]checked for malware[/comment]</curation>
  <collection>data</collection>
</metadata>
