<?xml version="1.0" encoding="UTF-8"?>
<metadata>
  <identifier>AMJ_BarrelData_4622_e5776ca3-d142-4c02-8c70-3d95685d6fef.2013-11-26-02-15-48-094205-_E</identifier>
  <collection>amjbarreldata</collection>
  <description>Arcmaj3 data. Barrel 4622, e5776ca3-d142-4c02-8c70-3d95685d6fef</description>
  <mediatype>web</mediatype>
  <subject>Arcmaj3; WARC; snapshot; archive; Arcmaj3BarrelData</subject>
  <title>Arcmaj3 data. Barrel 4622, e5776ca3-d142-4c02-8c70-3d95685d6fef</title>
  <publicdate>2013-11-26 07:15:55</publicdate>
  <uploader>worldpeacehaven@gmail.com</uploader>
  <addeddate>2013-11-26 07:15:55</addeddate>
  <curation>[curator]malware@archive.org[/curator][date]20140314033220[/date][comment]checked for malware[/comment]</curation>
  <collection>data</collection>
</metadata>
