<?xml version="1.0" encoding="UTF-8"?>
<metadata>
  <identifier>WARCdealer_BarrelData_rochuwd_6306ace0-c8fb-424e-90fb-ae512ff2592c.2016-03-16-01-00-49-780621-_E</identifier>
  <publicdate>2016-03-16 00:01:10</publicdate>
  <title>WARCdealer_BarrelData_rochuwd_6306ace0-c8fb-424e-90fb-ae512ff2592c.2016-03-16-01-00-49-780621-_E</title>
  <mediatype>data</mediatype>
  <collection>opensource</collection>
  <uploader>worldpeacehaven@gmail.com</uploader>
  <addeddate>2016-03-16 00:01:10</addeddate>
  <curation>[curator]validator@archive.org[/curator][date]20160316000209[/date][comment]checked for malware[/comment]</curation>
</metadata>
