<?xml version="1.0" encoding="UTF-8"?>
<files>
  <file name="2780.coal4" source="original">
    <format>Unknown</format>
    <mtime>1403981612</mtime>
    <size>1797</size>
    <md5>dace205171fc3b576be6e578db998058</md5>
    <crc32>98e297d5</crc32>
    <sha1>f5b22b7154bb23d0dbf795fc8e87f132478c968e</sha1>
  </file>
  <file name="2.7888.COALPROJECT.RECORD33_meta.sqlite" source="original">
    <format>Metadata</format>
    <mtime>1403981616</mtime>
    <size>6144</size>
    <md5>0c547e01c72de7b520eea5d0548518d4</md5>
    <crc32>314c9680</crc32>
    <sha1>e79dbc12080007e480516cfff4d22967ecd6176e</sha1>
  </file>
  <file name="2.7888.COALPROJECT.RECORD33_meta.xml" source="original">
    <format>Metadata</format>
    <mtime>1405462746</mtime>
    <size>501</size>
    <md5>44d0fdc72063fdf5c0dc7c2a71377ca0</md5>
    <crc32>d8cb2901</crc32>
    <sha1>a0a153f8cdcfe0e02e04f9ae0b103f362bd9398b</sha1>
  </file>
  <file name="2.7888.COALPROJECT.RECORD33_archive.torrent" source="metadata">
    <btih>0c5a07b41fe2dce35abe07f58a6f9edd17f68514</btih>
    <mtime>1405462746</mtime>
    <size>1773</size>
    <md5>7769c76248d778a6f2398ee8f140e920</md5>
    <crc32>13560f63</crc32>
    <sha1>3cc150edb917719bec0835f20d5b3d9ee521cabf</sha1>
    <format>Archive BitTorrent</format>
  </file>
  <file name="2.7888.COALPROJECT.RECORD33_files.xml" source="original">
    <format>Metadata</format>
    <md5>745368cd1b704812614df4e683269a75</md5>
  </file>
</files>
