<?xml version="1.0" encoding="UTF-8"?>
<files>
  <file name="5.0797.COALPROJECT.RECORD33_meta.sqlite" source="original">
    <format>Metadata</format>
    <mtime>1404104132</mtime>
    <size>6144</size>
    <md5>f73d94699ac185cda557d67b857e043e</md5>
    <crc32>80a09239</crc32>
    <sha1>142f48e54c7139f1dc3dfb4ca16bf737d6be9e5e</sha1>
  </file>
  <file name="5070.coal4" source="original">
    <format>Unknown</format>
    <mtime>1404104129</mtime>
    <size>2093</size>
    <md5>eaed2904699327d490904042b48daf29</md5>
    <crc32>cf776492</crc32>
    <sha1>85ea11b4fa95f2990f51abecc8bd6b609266a3c4</sha1>
  </file>
  <file name="5.0797.COALPROJECT.RECORD33_meta.xml" source="original">
    <format>Metadata</format>
    <mtime>1405462152</mtime>
    <size>501</size>
    <md5>59591b9404ffa0b86d7fc5424aed9009</md5>
    <crc32>4a51fd1c</crc32>
    <sha1>aed10f3a140ad01228841603b1869213ba912c82</sha1>
  </file>
  <file name="5.0797.COALPROJECT.RECORD33_archive.torrent" source="metadata">
    <btih>4efba8796d430e1ee5ec9ed3c0170b829e1f84a8</btih>
    <mtime>1405462153</mtime>
    <size>1771</size>
    <md5>cc36c481adeb30114a7af4d9d2c1b2c3</md5>
    <crc32>eda0fd12</crc32>
    <sha1>8c15d97a4d2426be4b1a4db056a029b72f308749</sha1>
    <format>Archive BitTorrent</format>
  </file>
  <file name="5.0797.COALPROJECT.RECORD33_files.xml" source="original">
    <format>Metadata</format>
    <md5>f88c9b856856a6da56ded15976dc8df0</md5>
  </file>
</files>
