<?xml version="1.0" encoding="UTF-8"?>
<files>
  <file name="1.91286.COALPROJECT.RECORD33_meta.sqlite" source="original">
    <format>Metadata</format>
    <mtime>1403919188</mtime>
    <size>6144</size>
    <md5>53e420b5819b25b77e910e0e59c938c1</md5>
    <crc32>28292a72</crc32>
    <sha1>6cc5f3db918421428d16b6ed2f7449ad137e9e87</sha1>
  </file>
  <file name="1912.coal4" source="original">
    <format>Unknown</format>
    <mtime>1403919185</mtime>
    <size>4533125</size>
    <md5>52bf7a960d8d83ba48db222c247621e9</md5>
    <crc32>47fc9417</crc32>
    <sha1>2adcd9638063404a75c9d17036e586162ba53a33</sha1>
  </file>
  <file name="1.91286.COALPROJECT.RECORD33_meta.xml" source="original">
    <format>Metadata</format>
    <mtime>1405462932</mtime>
    <size>503</size>
    <md5>fef0af7a5119f7ee1980188aa09e0bc7</md5>
    <crc32>4abbfaff</crc32>
    <sha1>ff822dafd30c74d616d5ae0fadcc477386413bb7</sha1>
  </file>
  <file name="1.91286.COALPROJECT.RECORD33_archive.torrent" source="metadata">
    <btih>3e655b7dcb0ba05a69a4fe44670a91d1ae9537a3</btih>
    <mtime>1405462933</mtime>
    <size>1946</size>
    <md5>437844e114d0362eab4d708d3e8347ca</md5>
    <crc32>2ef3b20e</crc32>
    <sha1>0fcab3994f31e1d5fc63ce35ebff307f196804a0</sha1>
    <format>Archive BitTorrent</format>
  </file>
  <file name="1.91286.COALPROJECT.RECORD33_files.xml" source="original">
    <format>Metadata</format>
    <md5>56b92def9db3de8cd42fd4c49282d5bd</md5>
  </file>
</files>
