<?xml version="1.0" encoding="UTF-8"?>
<files>
  <file name="3844.coal4" source="original">
    <format>Unknown</format>
    <mtime>1404075783</mtime>
    <size>2137</size>
    <md5>2aec6fd1742803cb7b86f2e36de53c87</md5>
    <crc32>3d5983ae</crc32>
    <sha1>25289f28abcceea9704caeedc8e252ee1b13209d</sha1>
  </file>
  <file name="3.84493.COALPROJECT.RECORD33_meta.sqlite" source="original">
    <format>Metadata</format>
    <mtime>1404075786</mtime>
    <size>6144</size>
    <md5>e0915309e1ca421fdbc57b5fedbbb51a</md5>
    <crc32>bdf69f1b</crc32>
    <sha1>7dd4ce9129914396a2c123e48d74f66c0766cdca</sha1>
  </file>
  <file name="3.84493.COALPROJECT.RECORD33_meta.xml" source="original">
    <format>Metadata</format>
    <mtime>1405462463</mtime>
    <size>503</size>
    <md5>3f759317b72ef5db1eb76829496e652c</md5>
    <crc32>e6c53067</crc32>
    <sha1>026a69d518a8892ed27a5997ae0a7d6556f1adf3</sha1>
  </file>
  <file name="3.84493.COALPROJECT.RECORD33_archive.torrent" source="metadata">
    <btih>1ee5a820306ea5a95508e0b43806dea9e68f71a3</btih>
    <mtime>1405462464</mtime>
    <size>1780</size>
    <md5>28373b438cbc7eaf4c379cd56fa909b8</md5>
    <crc32>de178ba5</crc32>
    <sha1>93b23c7c80ab41c0c3b71d2fbf624ac5ad044c2b</sha1>
    <format>Archive BitTorrent</format>
  </file>
  <file name="3.84493.COALPROJECT.RECORD33_files.xml" source="original">
    <format>Metadata</format>
    <md5>4a887bd1109dfa68a43384dfcc435159</md5>
  </file>
</files>
