<?xml version="1.0" encoding="UTF-8"?>
<metadata>
  <identifier>WARCdealer_BarrelData_rochuwd_dec75cd7-49b8-4b76-a87f-26c444ae3158.2016-03-21-05-57-48-453744-_E</identifier>
  <publicdate>2016-03-21 04:57:55</publicdate>
  <title>WARCdealer_BarrelData_rochuwd_dec75cd7-49b8-4b76-a87f-26c444ae3158.2016-03-21-05-57-48-453744-_E</title>
  <mediatype>data</mediatype>
  <collection>opensource</collection>
  <uploader>worldpeacehaven@gmail.com</uploader>
  <addeddate>2016-03-21 04:57:55</addeddate>
  <curation>[curator]validator@archive.org[/curator][date]20160321045814[/date][comment]checked for malware[/comment]</curation>
</metadata>
