<?xml version="1.0" encoding="UTF-8"?>
<files>
  <file name="1.8384.COALPROJECT.RECORD33_meta.sqlite" source="original">
    <format>Metadata</format>
    <mtime>1403914794</mtime>
    <size>6144</size>
    <md5>3625513b09f50ce97b664c3973a7217f</md5>
    <crc32>783d5b45</crc32>
    <sha1>95252ee23cb12d2dfd596daf865a7096d1b0f500</sha1>
  </file>
  <file name="1830.coal4" source="original">
    <format>Unknown</format>
    <mtime>1403914790</mtime>
    <size>2521</size>
    <md5>39ddf24121cf38727eda5ac4adb1dded</md5>
    <crc32>543295da</crc32>
    <sha1>92020c0d87dd46e2b4a1c91eb4ce3fd7f830b138</sha1>
  </file>
  <file name="1.8384.COALPROJECT.RECORD33_meta.xml" source="original">
    <format>Metadata</format>
    <mtime>1405462953</mtime>
    <size>501</size>
    <md5>068f4ddd19ed8b62c7780c6c0d3cfc42</md5>
    <crc32>2a9dc29a</crc32>
    <sha1>c9c73b1a88303e7d32ea9da860567c7540c7e630</sha1>
  </file>
  <file name="1.8384.COALPROJECT.RECORD33_archive.torrent" source="metadata">
    <btih>97b74d9110ea6258c9f318aabb1a7d32a46bfcc5</btih>
    <mtime>1405462954</mtime>
    <size>1771</size>
    <md5>bf4dfa08300e89182b991045f380a741</md5>
    <crc32>aef0cd5a</crc32>
    <sha1>fefd9a9689c35ea937bd4b4acad39baa1c9444b5</sha1>
    <format>Archive BitTorrent</format>
  </file>
  <file name="1.8384.COALPROJECT.RECORD33_files.xml" source="original">
    <format>Metadata</format>
    <md5>b664c55f14600ba9836f9f0100d117df</md5>
  </file>
</files>
