<?xml version="1.0" encoding="UTF-8"?>
<files>
  <file name="Dragon's Call.flv-kAOsIF1Mlzw.mp4.description" source="original">
    <mtime>1430269409</mtime>
    <size>344</size>
    <md5>8c00317d1bcf52a5a70b51ec7cbf91bf</md5>
    <crc32>293b3994</crc32>
    <sha1>5483fc912eae93036d535b0f14886cf557acd2f5</sha1>
    <format>Unknown</format>
  </file>
  <file name="Dragon's Call.flv-kAOsIF1Mlzw.info.json" source="original">
    <mtime>1430269382</mtime>
    <size>23549</size>
    <md5>930039b6d9340183023427ba167a7b4e</md5>
    <crc32>2adcff2e</crc32>
    <sha1>76108c0c2960dbb2b4d9bdbfd672c6e34d45949c</sha1>
    <format>JSON</format>
  </file>
  <file name="Dragon's Call.flv-kAOsIF1Mlzw.mp4" source="original">
    <mtime>1430269404</mtime>
    <size>7071931</size>
    <md5>5cb7905e6d2c817f7f38d2197a2d500d</md5>
    <crc32>eb0e2efb</crc32>
    <sha1>f0e076a21fc3d7af8376db2dbe0edf5c0d815bd0</sha1>
    <format>MPEG4</format>
    <length>102.98</length>
    <height>360</height>
    <width>480</width>
  </file>
  <file name="Dragon's Call.flv-kAOsIF1Mlzw.jpg" source="original">
    <mtime>1430269397</mtime>
    <size>16444</size>
    <md5>f363ca749efa09f2090d14ac94b6efcf</md5>
    <crc32>f6f32e5e</crc32>
    <sha1>962ccbca49be220e102fd2bb7189caaa163b7482</sha1>
    <format>JPEG</format>
    <rotation>0</rotation>
  </file>
  <file name="DragonsCallflvkAOsIF1Mlzw_meta.sqlite" source="original">
    <mtime>1430269438</mtime>
    <size>15360</size>
    <md5>06b15008f3d132ab254542905246bbb9</md5>
    <crc32>c85bee28</crc32>
    <sha1>24975fc56f2f95ec8cc36af32bc90c9ed0c95534</sha1>
    <format>Metadata</format>
  </file>
  <file name="Dragon's Call.flv-kAOsIF1Mlzw.f134.mp4" source="original">
    <mtime>1430269393</mtime>
    <size>3770460</size>
    <md5>fdcc15e44471f9c5b39824ae978de8da</md5>
    <crc32>3e913eea</crc32>
    <sha1>5afb2d6ace7a14950933cdcffb413e705b2fa9e7</sha1>
    <format>MPEG4</format>
    <length>102.84</length>
    <height>360</height>
    <width>480</width>
  </file>
  <file name="Dragon's Call.flv-kAOsIF1Mlzw.f141.m4a" source="original">
    <mtime>1430269395</mtime>
    <size>3283926</size>
    <md5>df92e8f6495e9fff2e105040dde5b75d</md5>
    <crc32>b5857dca</crc32>
    <sha1>691d955eebd4287b6fbd96b2cc1baed11b31d972</sha1>
    <format>Apple Lossless Audio</format>
  </file>
  <file name="Dragon's Call.flv-kAOsIF1Mlzw.mp4.annotations.xml" source="original">
    <mtime>1430269406</mtime>
    <size>1220</size>
    <md5>1a38b30e4901be2d387517ca965b8232</md5>
    <crc32>56ac1acd</crc32>
    <sha1>605c34e3a3790a34e6f8d563cbe0ea9a4f6ed1d0</sha1>
    <format>Metadata</format>
  </file>
  <file name="DragonsCallflvkAOsIF1Mlzw_meta.xml" source="original">
    <mtime>1430270058</mtime>
    <size>1113</size>
    <format>Metadata</format>
    <md5>5c7557ca1fe3b7243c81285d5711bbc8</md5>
    <crc32>e5ef4833</crc32>
    <sha1>261ba151c1bd4364843d9ea55797d870fa534c59</sha1>
  </file>
  <file name="Dragon's Call.flv-kAOsIF1Mlzw.f134.ogv" source="derivative">
    <format>Ogg Video</format>
    <original>Dragon's Call.flv-kAOsIF1Mlzw.f134.mp4</original>
    <mtime>1430270223</mtime>
    <size>6632765</size>
    <md5>3d10b11c1a6be94a00bbc5aa471e16ff</md5>
    <crc32>ed3bba94</crc32>
    <sha1>38da773e3a7af6d69fc4fb6ac37679c66de81f4c</sha1>
    <length>102.88</length>
    <height>300</height>
    <width>400</width>
  </file>
  <file name="Dragon's Call.flv-kAOsIF1Mlzw.gif" source="derivative">
    <format>Animated GIF</format>
    <original>Dragon's Call.flv-kAOsIF1Mlzw.mp4</original>
    <mtime>1430270079</mtime>
    <size>280431</size>
    <md5>59bd3afce06b70000f900be024543395</md5>
    <crc32>28ef843d</crc32>
    <sha1>cb388c382434240fd498435aeacae026f5de62b1</sha1>
  </file>
  <file name="Dragon's Call.flv-kAOsIF1Mlzw.f141_esshigh.json.gz" source="derivative">
    <format>Essentia High GZ</format>
    <original>Dragon's Call.flv-kAOsIF1Mlzw.f141_esslow.json.gz</original>
    <mtime>1430270360</mtime>
    <size>1831</size>
    <md5>65426e9ac8b166e83ecaac014adc831b</md5>
    <crc32>44bbfef6</crc32>
    <sha1>44b0775826ee9f205430dd674dfa70b97e043b29</sha1>
  </file>
  <file name="Dragon's Call.flv-kAOsIF1Mlzw.f141.ogg" source="derivative">
    <format>Ogg Vorbis</format>
    <original>Dragon's Call.flv-kAOsIF1Mlzw.f141.m4a</original>
    <mtime>1430270147</mtime>
    <size>1055757</size>
    <md5>3aadcfd74d027371020beca328ae924c</md5>
    <crc32>fce0d399</crc32>
    <sha1>163dbf91a6d5a02c41b9b9e1900ae43ece386e47</sha1>
    <length>102.98</length>
    <height>0</height>
    <width>0</width>
  </file>
  <file name="Dragon's Call.flv-kAOsIF1Mlzw.f141.afpk" source="derivative">
    <format>Columbia Peaks</format>
    <original>Dragon's Call.flv-kAOsIF1Mlzw.f141.m4a</original>
    <mtime>1430270346</mtime>
    <size>21088</size>
    <md5>073f915523f3252ab760c2be4cc5d0a5</md5>
    <crc32>0b6cc686</crc32>
    <sha1>eaa799cf8210b4ff73c1750643b44874ee2614f2</sha1>
  </file>
  <file name="DragonsCallflvkAOsIF1Mlzw.thumbs/Dragon's Call.flv-kAOsIF1Mlzw_000087.jpg" source="derivative">
    <format>Thumbnail</format>
    <original>Dragon's Call.flv-kAOsIF1Mlzw.mp4</original>
    <mtime>1430270126</mtime>
    <size>1856</size>
    <md5>c23c7b05676b7b477ec88928e49a37be</md5>
    <crc32>2c82ac4f</crc32>
    <sha1>463bd54721111a0505c994f22939bd05c568fdd9</sha1>
  </file>
  <file name="DragonsCallflvkAOsIF1Mlzw.thumbs/Dragon's Call.flv-kAOsIF1Mlzw.f134_000032.jpg" source="derivative">
    <format>Thumbnail</format>
    <original>Dragon's Call.flv-kAOsIF1Mlzw.f134.mp4</original>
    <mtime>1430270101</mtime>
    <size>3045</size>
    <md5>3161a6ff228f388ff09c56eae6bf99fb</md5>
    <crc32>4fc5a09e</crc32>
    <sha1>6268963d1535781e6a1021faa7ccbaeb6ce5e249</sha1>
  </file>
  <file name="DragonsCallflvkAOsIF1Mlzw.thumbs/Dragon's Call.flv-kAOsIF1Mlzw_000022.jpg" source="derivative">
    <format>Thumbnail</format>
    <original>Dragon's Call.flv-kAOsIF1Mlzw.mp4</original>
    <mtime>1430270119</mtime>
    <size>3199</size>
    <md5>61725aa77188e358aa0c13d7c28029ed</md5>
    <crc32>311a3a4e</crc32>
    <sha1>a8fb9596eda81e72024219e2c39fbff4fe9fdd31</sha1>
  </file>
  <file name="DragonsCallflvkAOsIF1Mlzw.thumbs/Dragon's Call.flv-kAOsIF1Mlzw_000072.jpg" source="derivative">
    <format>Thumbnail</format>
    <original>Dragon's Call.flv-kAOsIF1Mlzw.mp4</original>
    <mtime>1430270125</mtime>
    <size>1812</size>
    <md5>6ff22cf879e99d0236999fb9d03f3160</md5>
    <crc32>00ca7f34</crc32>
    <sha1>750da7ad5bf70f7ff1115b7f8c7108c149e5f51d</sha1>
  </file>
  <file name="DragonsCallflvkAOsIF1Mlzw.thumbs/Dragon's Call.flv-kAOsIF1Mlzw_000062.jpg" source="derivative">
    <format>Thumbnail</format>
    <original>Dragon's Call.flv-kAOsIF1Mlzw.mp4</original>
    <mtime>1430270124</mtime>
    <size>1305</size>
    <md5>435fc4a14aa2d8ef06834f260034efa4</md5>
    <crc32>2aba32f0</crc32>
    <sha1>8fa5488d8b487c90a1957114d00a145acf0f11b5</sha1>
  </file>
  <file name="DragonsCallflvkAOsIF1Mlzw.thumbs/Dragon's Call.flv-kAOsIF1Mlzw.f134_000067.jpg" source="derivative">
    <format>Thumbnail</format>
    <original>Dragon's Call.flv-kAOsIF1Mlzw.f134.mp4</original>
    <mtime>1430270106</mtime>
    <size>2044</size>
    <md5>7881b4c2b7e9edf8b992ea4ee6ee875a</md5>
    <crc32>7f0adff5</crc32>
    <sha1>88897067e22cf976f2d62767204a39c1d528aac5</sha1>
  </file>
  <file name="DragonsCallflvkAOsIF1Mlzw.thumbs/Dragon's Call.flv-kAOsIF1Mlzw_000092.jpg" source="derivative">
    <format>Thumbnail</format>
    <original>Dragon's Call.flv-kAOsIF1Mlzw.mp4</original>
    <mtime>1430270127</mtime>
    <size>1360</size>
    <md5>266743a3513d12e386017fa9bbbf2901</md5>
    <crc32>e8e5335b</crc32>
    <sha1>dcb9ce52261069426ddb6fc4cf5fdfd336ecdb29</sha1>
  </file>
  <file name="DragonsCallflvkAOsIF1Mlzw.thumbs/Dragon's Call.flv-kAOsIF1Mlzw_000007.jpg" source="derivative">
    <format>Thumbnail</format>
    <original>Dragon's Call.flv-kAOsIF1Mlzw.mp4</original>
    <mtime>1430270117</mtime>
    <size>8266</size>
    <md5>38a7c7785e1bb2db572798beb37e5cc5</md5>
    <crc32>a37101d0</crc32>
    <sha1>292e64bb8b586b39ac13043f77ff7af960961d0a</sha1>
  </file>
  <file name="DragonsCallflvkAOsIF1Mlzw.thumbs/Dragon's Call.flv-kAOsIF1Mlzw.f134_000072.jpg" source="derivative">
    <format>Thumbnail</format>
    <original>Dragon's Call.flv-kAOsIF1Mlzw.f134.mp4</original>
    <mtime>1430270106</mtime>
    <size>1812</size>
    <md5>6ff22cf879e99d0236999fb9d03f3160</md5>
    <crc32>00ca7f34</crc32>
    <sha1>750da7ad5bf70f7ff1115b7f8c7108c149e5f51d</sha1>
  </file>
  <file name="DragonsCallflvkAOsIF1Mlzw.thumbs/Dragon's Call.flv-kAOsIF1Mlzw_000017.jpg" source="derivative">
    <format>Thumbnail</format>
    <original>Dragon's Call.flv-kAOsIF1Mlzw.mp4</original>
    <mtime>1430270119</mtime>
    <size>3701</size>
    <md5>f0b61e1896f0b1c70e30e0df33b27a8d</md5>
    <crc32>36ddaf11</crc32>
    <sha1>28ef45a64ebae52a1cf4b1243d6ff15454ef6022</sha1>
  </file>
  <file name="DragonsCallflvkAOsIF1Mlzw.thumbs/Dragon's Call.flv-kAOsIF1Mlzw_000042.jpg" source="derivative">
    <format>Thumbnail</format>
    <original>Dragon's Call.flv-kAOsIF1Mlzw.mp4</original>
    <mtime>1430270122</mtime>
    <size>2077</size>
    <md5>f41694aa7781bbb3ccfc51bf04184e28</md5>
    <crc32>2797a240</crc32>
    <sha1>e51e7063c41b5109b241ef400c2ea9d3be1e9fe5</sha1>
  </file>
  <file name="DragonsCallflvkAOsIF1Mlzw.thumbs/Dragon's Call.flv-kAOsIF1Mlzw.f134_000027.jpg" source="derivative">
    <format>Thumbnail</format>
    <original>Dragon's Call.flv-kAOsIF1Mlzw.f134.mp4</original>
    <mtime>1430270101</mtime>
    <size>1880</size>
    <md5>f1c1377c246d5a3eda59b25443cc2c77</md5>
    <crc32>43478dac</crc32>
    <sha1>3ecb3d928efe59600bdd41d4fd84dc98451b86ee</sha1>
  </file>
  <file name="DragonsCallflvkAOsIF1Mlzw.thumbs/Dragon's Call.flv-kAOsIF1Mlzw.f134_000022.jpg" source="derivative">
    <format>Thumbnail</format>
    <original>Dragon's Call.flv-kAOsIF1Mlzw.f134.mp4</original>
    <mtime>1430270100</mtime>
    <size>3199</size>
    <md5>61725aa77188e358aa0c13d7c28029ed</md5>
    <crc32>311a3a4e</crc32>
    <sha1>a8fb9596eda81e72024219e2c39fbff4fe9fdd31</sha1>
  </file>
  <file name="DragonsCallflvkAOsIF1Mlzw.thumbs/Dragon's Call.flv-kAOsIF1Mlzw_000097.jpg" source="derivative">
    <format>Thumbnail</format>
    <original>Dragon's Call.flv-kAOsIF1Mlzw.mp4</original>
    <mtime>1430270127</mtime>
    <size>1619</size>
    <md5>9c9db1fbfb6f4a0d77fafcef630110e2</md5>
    <crc32>5b2061e6</crc32>
    <sha1>83adf563e72a17d4245b570c1d28fe6a69787927</sha1>
  </file>
  <file name="DragonsCallflvkAOsIF1Mlzw.thumbs/Dragon's Call.flv-kAOsIF1Mlzw.f134_000052.jpg" source="derivative">
    <format>Thumbnail</format>
    <original>Dragon's Call.flv-kAOsIF1Mlzw.f134.mp4</original>
    <mtime>1430270104</mtime>
    <size>2096</size>
    <md5>c76a1f9fa62f1ffff4e11315bdb52114</md5>
    <crc32>6145ae02</crc32>
    <sha1>54f630a7a48051de0e66a7e0dc8cf67bc0100d79</sha1>
  </file>
  <file name="DragonsCallflvkAOsIF1Mlzw.thumbs/Dragon's Call.flv-kAOsIF1Mlzw.f134_000087.jpg" source="derivative">
    <format>Thumbnail</format>
    <original>Dragon's Call.flv-kAOsIF1Mlzw.f134.mp4</original>
    <mtime>1430270108</mtime>
    <size>1856</size>
    <md5>c23c7b05676b7b477ec88928e49a37be</md5>
    <crc32>2c82ac4f</crc32>
    <sha1>463bd54721111a0505c994f22939bd05c568fdd9</sha1>
  </file>
  <file name="DragonsCallflvkAOsIF1Mlzw.thumbs/Dragon's Call.flv-kAOsIF1Mlzw.f134_000037.jpg" source="derivative">
    <format>Thumbnail</format>
    <original>Dragon's Call.flv-kAOsIF1Mlzw.f134.mp4</original>
    <mtime>1430270102</mtime>
    <size>2704</size>
    <md5>00e58580256a6b0d12d7e4fa264be03e</md5>
    <crc32>75330910</crc32>
    <sha1>cee648f7ccaca77eccab507cf6110bd0ee7d9464</sha1>
  </file>
  <file name="DragonsCallflvkAOsIF1Mlzw.thumbs/Dragon's Call.flv-kAOsIF1Mlzw.f134_000047.jpg" source="derivative">
    <format>Thumbnail</format>
    <original>Dragon's Call.flv-kAOsIF1Mlzw.f134.mp4</original>
    <mtime>1430270103</mtime>
    <size>2248</size>
    <md5>056ed53ce37cc01c7e4645641ad7971a</md5>
    <crc32>90c00b77</crc32>
    <sha1>3ed6cbc751356f5e5f311c40919c7a50b1c751c3</sha1>
  </file>
  <file name="DragonsCallflvkAOsIF1Mlzw.thumbs/Dragon's Call.flv-kAOsIF1Mlzw_000032.jpg" source="derivative">
    <format>Thumbnail</format>
    <original>Dragon's Call.flv-kAOsIF1Mlzw.mp4</original>
    <mtime>1430270121</mtime>
    <size>3045</size>
    <md5>3161a6ff228f388ff09c56eae6bf99fb</md5>
    <crc32>4fc5a09e</crc32>
    <sha1>6268963d1535781e6a1021faa7ccbaeb6ce5e249</sha1>
  </file>
  <file name="DragonsCallflvkAOsIF1Mlzw.thumbs/Dragon's Call.flv-kAOsIF1Mlzw.f134_000012.jpg" source="derivative">
    <format>Thumbnail</format>
    <original>Dragon's Call.flv-kAOsIF1Mlzw.f134.mp4</original>
    <mtime>1430270099</mtime>
    <size>3050</size>
    <md5>a5876e6751444cba0dac5a545652d515</md5>
    <crc32>ca766797</crc32>
    <sha1>4159af587b9ff41175ef5f16b1c3614a7f2533c8</sha1>
  </file>
  <file name="DragonsCallflvkAOsIF1Mlzw.thumbs/Dragon's Call.flv-kAOsIF1Mlzw.f134_000092.jpg" source="derivative">
    <format>Thumbnail</format>
    <original>Dragon's Call.flv-kAOsIF1Mlzw.f134.mp4</original>
    <mtime>1430270108</mtime>
    <size>1360</size>
    <md5>266743a3513d12e386017fa9bbbf2901</md5>
    <crc32>e8e5335b</crc32>
    <sha1>dcb9ce52261069426ddb6fc4cf5fdfd336ecdb29</sha1>
  </file>
  <file name="DragonsCallflvkAOsIF1Mlzw.thumbs/Dragon's Call.flv-kAOsIF1Mlzw_000067.jpg" source="derivative">
    <format>Thumbnail</format>
    <original>Dragon's Call.flv-kAOsIF1Mlzw.mp4</original>
    <mtime>1430270124</mtime>
    <size>2044</size>
    <md5>7881b4c2b7e9edf8b992ea4ee6ee875a</md5>
    <crc32>7f0adff5</crc32>
    <sha1>88897067e22cf976f2d62767204a39c1d528aac5</sha1>
  </file>
  <file name="DragonsCallflvkAOsIF1Mlzw.thumbs/Dragon's Call.flv-kAOsIF1Mlzw.f134_000042.jpg" source="derivative">
    <format>Thumbnail</format>
    <original>Dragon's Call.flv-kAOsIF1Mlzw.f134.mp4</original>
    <mtime>1430270103</mtime>
    <size>2077</size>
    <md5>f41694aa7781bbb3ccfc51bf04184e28</md5>
    <crc32>2797a240</crc32>
    <sha1>e51e7063c41b5109b241ef400c2ea9d3be1e9fe5</sha1>
  </file>
  <file name="DragonsCallflvkAOsIF1Mlzw.thumbs/Dragon's Call.flv-kAOsIF1Mlzw.f134_000001.jpg" source="derivative">
    <format>Thumbnail</format>
    <original>Dragon's Call.flv-kAOsIF1Mlzw.f134.mp4</original>
    <mtime>1430270098</mtime>
    <size>8155</size>
    <md5>3b9aae1027219fb33171b1bebf18a503</md5>
    <crc32>b4581236</crc32>
    <sha1>b09734bce3081d3dc1d625cab672ff7152c212e4</sha1>
  </file>
  <file name="DragonsCallflvkAOsIF1Mlzw.thumbs/Dragon's Call.flv-kAOsIF1Mlzw.f134_000097.jpg" source="derivative">
    <format>Thumbnail</format>
    <original>Dragon's Call.flv-kAOsIF1Mlzw.f134.mp4</original>
    <mtime>1430270108</mtime>
    <size>1619</size>
    <md5>9c9db1fbfb6f4a0d77fafcef630110e2</md5>
    <crc32>5b2061e6</crc32>
    <sha1>83adf563e72a17d4245b570c1d28fe6a69787927</sha1>
  </file>
  <file name="DragonsCallflvkAOsIF1Mlzw.thumbs/Dragon's Call.flv-kAOsIF1Mlzw.f134_000017.jpg" source="derivative">
    <format>Thumbnail</format>
    <original>Dragon's Call.flv-kAOsIF1Mlzw.f134.mp4</original>
    <mtime>1430270100</mtime>
    <size>3701</size>
    <md5>f0b61e1896f0b1c70e30e0df33b27a8d</md5>
    <crc32>36ddaf11</crc32>
    <sha1>28ef45a64ebae52a1cf4b1243d6ff15454ef6022</sha1>
  </file>
  <file name="DragonsCallflvkAOsIF1Mlzw.thumbs/Dragon's Call.flv-kAOsIF1Mlzw.f134_000102.jpg" source="derivative">
    <format>Thumbnail</format>
    <original>Dragon's Call.flv-kAOsIF1Mlzw.f134.mp4</original>
    <mtime>1430270109</mtime>
    <size>1617</size>
    <md5>058903d22d61cadfc2b9ba1c25f3ba10</md5>
    <crc32>0d70982d</crc32>
    <sha1>88a4922ea8cc928b500c1bb35f6b70a49d9a10a5</sha1>
  </file>
  <file name="DragonsCallflvkAOsIF1Mlzw.thumbs/Dragon's Call.flv-kAOsIF1Mlzw_000027.jpg" source="derivative">
    <format>Thumbnail</format>
    <original>Dragon's Call.flv-kAOsIF1Mlzw.mp4</original>
    <mtime>1430270120</mtime>
    <size>1880</size>
    <md5>f1c1377c246d5a3eda59b25443cc2c77</md5>
    <crc32>43478dac</crc32>
    <sha1>3ecb3d928efe59600bdd41d4fd84dc98451b86ee</sha1>
  </file>
  <file name="DragonsCallflvkAOsIF1Mlzw.thumbs/Dragon's Call.flv-kAOsIF1Mlzw_000001.jpg" source="derivative">
    <format>Thumbnail</format>
    <original>Dragon's Call.flv-kAOsIF1Mlzw.mp4</original>
    <mtime>1430270117</mtime>
    <size>8155</size>
    <md5>3b9aae1027219fb33171b1bebf18a503</md5>
    <crc32>b4581236</crc32>
    <sha1>b09734bce3081d3dc1d625cab672ff7152c212e4</sha1>
  </file>
  <file name="DragonsCallflvkAOsIF1Mlzw.thumbs/Dragon's Call.flv-kAOsIF1Mlzw.f134_000077.jpg" source="derivative">
    <format>Thumbnail</format>
    <original>Dragon's Call.flv-kAOsIF1Mlzw.f134.mp4</original>
    <mtime>1430270107</mtime>
    <size>1867</size>
    <md5>fa2f4751b457640a3bda656527a55c9f</md5>
    <crc32>30bd4441</crc32>
    <sha1>b4f2c28c938395d9965036ea98387ffd2c9680b4</sha1>
  </file>
  <file name="DragonsCallflvkAOsIF1Mlzw.thumbs/Dragon's Call.flv-kAOsIF1Mlzw.f134_000062.jpg" source="derivative">
    <format>Thumbnail</format>
    <original>Dragon's Call.flv-kAOsIF1Mlzw.f134.mp4</original>
    <mtime>1430270105</mtime>
    <size>1305</size>
    <md5>435fc4a14aa2d8ef06834f260034efa4</md5>
    <crc32>2aba32f0</crc32>
    <sha1>8fa5488d8b487c90a1957114d00a145acf0f11b5</sha1>
  </file>
  <file name="DragonsCallflvkAOsIF1Mlzw.thumbs/Dragon's Call.flv-kAOsIF1Mlzw_000047.jpg" source="derivative">
    <format>Thumbnail</format>
    <original>Dragon's Call.flv-kAOsIF1Mlzw.mp4</original>
    <mtime>1430270122</mtime>
    <size>2248</size>
    <md5>056ed53ce37cc01c7e4645641ad7971a</md5>
    <crc32>90c00b77</crc32>
    <sha1>3ed6cbc751356f5e5f311c40919c7a50b1c751c3</sha1>
  </file>
  <file name="DragonsCallflvkAOsIF1Mlzw.thumbs/Dragon's Call.flv-kAOsIF1Mlzw_000077.jpg" source="derivative">
    <format>Thumbnail</format>
    <original>Dragon's Call.flv-kAOsIF1Mlzw.mp4</original>
    <mtime>1430270125</mtime>
    <size>1867</size>
    <md5>fa2f4751b457640a3bda656527a55c9f</md5>
    <crc32>30bd4441</crc32>
    <sha1>b4f2c28c938395d9965036ea98387ffd2c9680b4</sha1>
  </file>
  <file name="DragonsCallflvkAOsIF1Mlzw.thumbs/Dragon's Call.flv-kAOsIF1Mlzw_000102.jpg" source="derivative">
    <format>Thumbnail</format>
    <original>Dragon's Call.flv-kAOsIF1Mlzw.mp4</original>
    <mtime>1430270127</mtime>
    <size>1617</size>
    <md5>058903d22d61cadfc2b9ba1c25f3ba10</md5>
    <crc32>0d70982d</crc32>
    <sha1>88a4922ea8cc928b500c1bb35f6b70a49d9a10a5</sha1>
  </file>
  <file name="DragonsCallflvkAOsIF1Mlzw.thumbs/Dragon's Call.flv-kAOsIF1Mlzw_000052.jpg" source="derivative">
    <format>Thumbnail</format>
    <original>Dragon's Call.flv-kAOsIF1Mlzw.mp4</original>
    <mtime>1430270123</mtime>
    <size>2096</size>
    <md5>c76a1f9fa62f1ffff4e11315bdb52114</md5>
    <crc32>6145ae02</crc32>
    <sha1>54f630a7a48051de0e66a7e0dc8cf67bc0100d79</sha1>
  </file>
  <file name="DragonsCallflvkAOsIF1Mlzw.thumbs/Dragon's Call.flv-kAOsIF1Mlzw_000012.jpg" source="derivative">
    <format>Thumbnail</format>
    <original>Dragon's Call.flv-kAOsIF1Mlzw.mp4</original>
    <mtime>1430270118</mtime>
    <size>3050</size>
    <md5>a5876e6751444cba0dac5a545652d515</md5>
    <crc32>ca766797</crc32>
    <sha1>4159af587b9ff41175ef5f16b1c3614a7f2533c8</sha1>
  </file>
  <file name="DragonsCallflvkAOsIF1Mlzw.thumbs/Dragon's Call.flv-kAOsIF1Mlzw.f134_000082.jpg" source="derivative">
    <format>Thumbnail</format>
    <original>Dragon's Call.flv-kAOsIF1Mlzw.f134.mp4</original>
    <mtime>1430270107</mtime>
    <size>1817</size>
    <md5>9840d43909949f16f2b4f466d7534076</md5>
    <crc32>ca8b500b</crc32>
    <sha1>381c2c653e43352d1547eeb21820a44564e958e4</sha1>
  </file>
  <file name="DragonsCallflvkAOsIF1Mlzw.thumbs/Dragon's Call.flv-kAOsIF1Mlzw.f134_000057.jpg" source="derivative">
    <format>Thumbnail</format>
    <original>Dragon's Call.flv-kAOsIF1Mlzw.f134.mp4</original>
    <mtime>1430270105</mtime>
    <size>2264</size>
    <md5>85716e12a946ee2716c0508dd15d4ece</md5>
    <crc32>c7d6e585</crc32>
    <sha1>da76acb9ba9a7ce4b5e8e33dbb3f82ed25ce4aef</sha1>
  </file>
  <file name="DragonsCallflvkAOsIF1Mlzw.thumbs/Dragon's Call.flv-kAOsIF1Mlzw_000082.jpg" source="derivative">
    <format>Thumbnail</format>
    <original>Dragon's Call.flv-kAOsIF1Mlzw.mp4</original>
    <mtime>1430270126</mtime>
    <size>1817</size>
    <md5>9840d43909949f16f2b4f466d7534076</md5>
    <crc32>ca8b500b</crc32>
    <sha1>381c2c653e43352d1547eeb21820a44564e958e4</sha1>
  </file>
  <file name="DragonsCallflvkAOsIF1Mlzw.thumbs/Dragon's Call.flv-kAOsIF1Mlzw.f134_000007.jpg" source="derivative">
    <format>Thumbnail</format>
    <original>Dragon's Call.flv-kAOsIF1Mlzw.f134.mp4</original>
    <mtime>1430270098</mtime>
    <size>8266</size>
    <md5>38a7c7785e1bb2db572798beb37e5cc5</md5>
    <crc32>a37101d0</crc32>
    <sha1>292e64bb8b586b39ac13043f77ff7af960961d0a</sha1>
  </file>
  <file name="DragonsCallflvkAOsIF1Mlzw.thumbs/Dragon's Call.flv-kAOsIF1Mlzw_000037.jpg" source="derivative">
    <format>Thumbnail</format>
    <original>Dragon's Call.flv-kAOsIF1Mlzw.mp4</original>
    <mtime>1430270121</mtime>
    <size>2704</size>
    <md5>00e58580256a6b0d12d7e4fa264be03e</md5>
    <crc32>75330910</crc32>
    <sha1>cee648f7ccaca77eccab507cf6110bd0ee7d9464</sha1>
  </file>
  <file name="DragonsCallflvkAOsIF1Mlzw.thumbs/Dragon's Call.flv-kAOsIF1Mlzw_000057.jpg" source="derivative">
    <format>Thumbnail</format>
    <original>Dragon's Call.flv-kAOsIF1Mlzw.mp4</original>
    <mtime>1430270123</mtime>
    <size>2264</size>
    <md5>85716e12a946ee2716c0508dd15d4ece</md5>
    <crc32>c7d6e585</crc32>
    <sha1>da76acb9ba9a7ce4b5e8e33dbb3f82ed25ce4aef</sha1>
  </file>
  <file name="Dragon's Call.flv-kAOsIF1Mlzw_thumb.jpg" source="derivative">
    <format>JPEG Thumb</format>
    <original>Dragon's Call.flv-kAOsIF1Mlzw.jpg</original>
    <mtime>1430270325</mtime>
    <size>5459</size>
    <md5>b9cb59030e0a9834bf81c22c31676f03</md5>
    <crc32>ac3e8f26</crc32>
    <sha1>13ad179c6047144768ad576775dbdde8530fa338</sha1>
  </file>
  <file name="Dragon's Call.flv-kAOsIF1Mlzw.f134.gif" source="derivative">
    <format>Animated GIF</format>
    <original>Dragon's Call.flv-kAOsIF1Mlzw.f134.mp4</original>
    <mtime>1430270096</mtime>
    <size>280431</size>
    <md5>59bd3afce06b70000f900be024543395</md5>
    <crc32>28ef843d</crc32>
    <sha1>cb388c382434240fd498435aeacae026f5de62b1</sha1>
  </file>
  <file name="Dragon's Call.flv-kAOsIF1Mlzw.f141.mp3" source="derivative">
    <bitrate>165</bitrate>
    <length>01:43</length>
    <format>VBR MP3</format>
    <original>Dragon's Call.flv-kAOsIF1Mlzw.f141.m4a</original>
    <mtime>1430270142</mtime>
    <size>2172416</size>
    <md5>d95386483a94f6619f5cb98d7247dcfc</md5>
    <crc32>a1b7d5be</crc32>
    <sha1>9d4c194d1e6d7c41b76a8fddfafe14412a5d31f8</sha1>
    <height>0</height>
    <width>0</width>
  </file>
  <file name="Dragon's Call.flv-kAOsIF1Mlzw.ogv" source="derivative">
    <format>Ogg Video</format>
    <original>Dragon's Call.flv-kAOsIF1Mlzw.mp4</original>
    <mtime>1430270322</mtime>
    <size>8085300</size>
    <md5>e118cdd18747db285873839198ee7af3</md5>
    <crc32>eda6781c</crc32>
    <sha1>2e9b44e8dc785f28d2eecfe12aa6ae934401275e</sha1>
    <length>102.98</length>
    <height>300</height>
    <width>400</width>
  </file>
  <file name="Dragon's Call.flv-kAOsIF1Mlzw.f141_esslow.json.gz" source="derivative">
    <format>Essentia Low GZ</format>
    <original>Dragon's Call.flv-kAOsIF1Mlzw.f141.m4a</original>
    <mtime>1430270339</mtime>
    <size>22362</size>
    <md5>d322290fc1b865403276416e209404a5</md5>
    <crc32>89042e17</crc32>
    <sha1>cefc0181a9a5ae94458af54794f7a69d6a7df023</sha1>
  </file>
  <file name="Dragon's Call.flv-kAOsIF1Mlzw.f141.png" source="derivative">
    <format>PNG</format>
    <original>Dragon's Call.flv-kAOsIF1Mlzw.f141.m4a</original>
    <mtime>1430270329</mtime>
    <size>9737</size>
    <md5>94c1e1d1df162fcb042faa81e619543f</md5>
    <crc32>f4d93244</crc32>
    <sha1>5793969811d850a2d31f7a0779c44d4ccb2b60b8</sha1>
  </file>
  <file name="DragonsCallflvkAOsIF1Mlzw_archive.torrent" source="metadata">
    <btih>6b6465bd552ac4aa20e4520a3938290c46286921</btih>
    <mtime>1430270367</mtime>
    <size>6329</size>
    <md5>1085b53df9da6dc34e77726edd2af3c9</md5>
    <crc32>8c287ebf</crc32>
    <sha1>06102b7a3ea5f23f79f31d7d91907a5a4492d6a6</sha1>
    <format>Archive BitTorrent</format>
  </file>
  <file name="DragonsCallflvkAOsIF1Mlzw_files.xml" source="original">
    <format>Metadata</format>
    <md5>266f41359dfdf6cedef194a45cf62783</md5>
  </file>
</files>
