<?xml version="1.0" encoding="UTF-8"?>
<files>
  <file name="3319.coal4" source="original">
    <format>Unknown</format>
    <mtime>1404010656</mtime>
    <size>2777</size>
    <md5>119b3a367de22217ee5719e93e5855b7</md5>
    <crc32>f9b4f2a0</crc32>
    <sha1>a85fecc95d770806ca721c68efc396a772be16ac</sha1>
  </file>
  <file name="3.31942.COALPROJECT.RECORD33_meta.sqlite" source="original">
    <format>Metadata</format>
    <mtime>1404010661</mtime>
    <size>6144</size>
    <md5>923ddf2aca2c882552dfa1932f849215</md5>
    <crc32>3b953e5b</crc32>
    <sha1>16cef40b93fe743830aea200f5a3af65ce804dd8</sha1>
  </file>
  <file name="3.31942.COALPROJECT.RECORD33_meta.xml" source="original">
    <format>Metadata</format>
    <mtime>1405462613</mtime>
    <size>503</size>
    <md5>624c5c2d05b5eb577b9f237df85d4fdf</md5>
    <crc32>7b7640b1</crc32>
    <sha1>ff1661c01ca67632de42bb1a4a4b274f09ea5a8b</sha1>
  </file>
  <file name="3.31942.COALPROJECT.RECORD33_archive.torrent" source="metadata">
    <btih>00a85df517b6a3cffc55802b572ec33f497a1e7b</btih>
    <mtime>1405462614</mtime>
    <size>1782</size>
    <md5>75cc2c3078d097499d9a997ee1cec1b9</md5>
    <crc32>5aa0b3a4</crc32>
    <sha1>36370ac0bd16ce1c24b4b1c556a6a1036d4eb7c2</sha1>
    <format>Archive BitTorrent</format>
  </file>
  <file name="3.31942.COALPROJECT.RECORD33_files.xml" source="original">
    <format>Metadata</format>
    <md5>5e591bd2691844c953fc5f268dc11e2b</md5>
  </file>
</files>
