<?xml version="1.0" encoding="UTF-8"?>
<metadata>
  <identifier>AMJ_BarrelData_5033_2ca90ed3-8eb7-40da-ba7d-40f414d0169d.2013-11-26-04-24-44-451954-_E</identifier>
  <collection>amjbarreldata</collection>
  <description>Arcmaj3 data. Barrel 5033, 2ca90ed3-8eb7-40da-ba7d-40f414d0169d</description>
  <mediatype>web</mediatype>
  <subject>Arcmaj3; WARC; snapshot; archive; Arcmaj3BarrelData</subject>
  <title>Arcmaj3 data. Barrel 5033, 2ca90ed3-8eb7-40da-ba7d-40f414d0169d</title>
  <publicdate>2013-11-26 09:25:36</publicdate>
  <uploader>worldpeacehaven@gmail.com</uploader>
  <addeddate>2013-11-26 09:25:36</addeddate>
  <curation>[curator]malware@archive.org[/curator][date]20140314032828[/date][comment]checked for malware[/comment]</curation>
  <collection>data</collection>
</metadata>
