<?xml version="1.0" encoding="UTF-8"?>
<metadata>
  <identifier>WARCdealer_BarrelData_rochuwd_c1ffaa98-4649-4e38-898b-dd30af403b2e.2016-03-10-17-45-44-654170-_E</identifier>
  <publicdate>2016-03-10 16:46:03</publicdate>
  <title>WARCdealer_BarrelData_rochuwd_c1ffaa98-4649-4e38-898b-dd30af403b2e.2016-03-10-17-45-44-654170-_E</title>
  <mediatype>data</mediatype>
  <collection>opensource</collection>
  <uploader>worldpeacehaven@gmail.com</uploader>
  <addeddate>2016-03-10 16:46:03</addeddate>
  <curation>[curator]validator@archive.org[/curator][date]20160310164622[/date][comment]checked for malware[/comment]</curation>
</metadata>
