<?xml version="1.0" encoding="UTF-8"?>
<metadata>
  <identifier>WARCdealer_BarrelData_rochuwd_8626710b-30ff-4957-9bb3-1caf94ef284b.2016-03-10-22-52-30-829826-_E</identifier>
  <publicdate>2016-03-10 21:53:02</publicdate>
  <title>WARCdealer_BarrelData_rochuwd_8626710b-30ff-4957-9bb3-1caf94ef284b.2016-03-10-22-52-30-829826-_E</title>
  <mediatype>data</mediatype>
  <collection>opensource</collection>
  <uploader>worldpeacehaven@gmail.com</uploader>
  <addeddate>2016-03-10 21:53:02</addeddate>
  <curation>[curator]validator@archive.org[/curator][date]20160310215324[/date][comment]checked for malware[/comment]</curation>
</metadata>
