<?xml version="1.0" encoding="UTF-8"?>
<metadata>
  <identifier>WARCdealer_BarrelData_rochuwd_18ff30e4-36fa-48ba-a010-3dff9d651152.2016-03-07-18-22-13-173729-_E</identifier>
  <publicdate>2016-03-07 17:22:21</publicdate>
  <title>WARCdealer_BarrelData_rochuwd_18ff30e4-36fa-48ba-a010-3dff9d651152.2016-03-07-18-22-13-173729-_E</title>
  <mediatype>data</mediatype>
  <collection>opensource</collection>
  <uploader>worldpeacehaven@gmail.com</uploader>
  <addeddate>2016-03-07 17:22:21</addeddate>
  <curation>[curator]validator@archive.org[/curator][date]20160307172250[/date][comment]checked for malware[/comment]</curation>
</metadata>
