<?xml version="1.0" encoding="UTF-8"?>
<files>
  <file name="1237.coal4" source="original">
    <format>Unknown</format>
    <mtime>1403812281</mtime>
    <size>2093</size>
    <md5>7e9f8c88cdb342bf468d9f3baa8258e3</md5>
    <crc32>4ba6ee1f</crc32>
    <sha1>379b92c74de917e3d0601dc6299b3bbf4f11c8b9</sha1>
  </file>
  <file name="1.23743.COALPROJECT.RECORD33_meta.sqlite" source="original">
    <format>Metadata</format>
    <mtime>1403812285</mtime>
    <size>6144</size>
    <md5>7163c940a46cd7c8a37539fa18ea2147</md5>
    <crc32>2ac562d5</crc32>
    <sha1>9e441ec5507c4cc7018a6936852ea72fc5df35c2</sha1>
  </file>
  <file name="1.23743.COALPROJECT.RECORD33_meta.xml" source="original">
    <format>Metadata</format>
    <mtime>1405463104</mtime>
    <size>503</size>
    <md5>46fdcadde796218ebca767f806b81722</md5>
    <crc32>c3c29e43</crc32>
    <sha1>c238e93e9a51af03412d50efe38987e0c98b9f1f</sha1>
  </file>
  <file name="1.23743.COALPROJECT.RECORD33_archive.torrent" source="metadata">
    <btih>1802dba9301dec78240307207fab008a32547369</btih>
    <mtime>1405463104</mtime>
    <size>1782</size>
    <md5>885f5fed3e4849a555a848961307617a</md5>
    <crc32>155c196b</crc32>
    <sha1>b46ff7c77c95a24dbf9e52b55a10b5c942955227</sha1>
    <format>Archive BitTorrent</format>
  </file>
  <file name="1.23743.COALPROJECT.RECORD33_files.xml" source="original">
    <format>Metadata</format>
    <md5>e6cb04a6722f0060d956b47caa37baf6</md5>
  </file>
</files>
