<?xml version="1.0" encoding="UTF-8"?>
<metadata>
  <identifier>WARCdealer_BarrelData_rochuwd_594b7ff6-25b2-4599-8555-0844f27c5e4f.2016-03-15-19-58-11-493425-_E</identifier>
  <publicdate>2016-03-15 18:58:44</publicdate>
  <title>WARCdealer_BarrelData_rochuwd_594b7ff6-25b2-4599-8555-0844f27c5e4f.2016-03-15-19-58-11-493425-_E</title>
  <mediatype>data</mediatype>
  <collection>opensource</collection>
  <uploader>worldpeacehaven@gmail.com</uploader>
  <addeddate>2016-03-15 18:58:44</addeddate>
  <curation>[curator]validator@archive.org[/curator][date]20160315185913[/date][comment]checked for malware[/comment]</curation>
</metadata>
