<?xml version="1.0" encoding="UTF-8"?>
<metadata>
  <identifier>WARCdealer_BarrelData_rochuwd_e6602912-9193-4e26-bcf1-772f9dc90cdb.2016-03-11-00-21-14-434010-_E</identifier>
  <publicdate>2016-03-10 23:21:25</publicdate>
  <title>WARCdealer_BarrelData_rochuwd_e6602912-9193-4e26-bcf1-772f9dc90cdb.2016-03-11-00-21-14-434010-_E</title>
  <mediatype>data</mediatype>
  <collection>opensource</collection>
  <uploader>worldpeacehaven@gmail.com</uploader>
  <addeddate>2016-03-10 23:21:25</addeddate>
  <curation>[curator]validator@archive.org[/curator][date]20160310232148[/date][comment]checked for malware[/comment]</curation>
</metadata>
