<?xml version="1.0" encoding="UTF-8"?>
<files>
  <file name="2264.coal4" source="original">
    <format>Unknown</format>
    <mtime>1403933965</mtime>
    <size>4533293</size>
    <md5>5c52a793c55c8a45fa4bd315fca8e6b5</md5>
    <crc32>2c0f0b83</crc32>
    <sha1>2df93a8b25cb327ad02272528fc0cd6ebfdc3482</sha1>
  </file>
  <file name="2.26441.COALPROJECT.RECORD33_meta.sqlite" source="original">
    <format>Metadata</format>
    <mtime>1403933968</mtime>
    <size>6144</size>
    <md5>31f16225133fe48affc30991c18849b5</md5>
    <crc32>34716fb8</crc32>
    <sha1>1a61e8e1517135740140861253ac03f5bdd746a5</sha1>
  </file>
  <file name="2.26441.COALPROJECT.RECORD33_meta.xml" source="original">
    <format>Metadata</format>
    <mtime>1405462857</mtime>
    <size>503</size>
    <md5>f7147d0b3171228d5418f47ff92203be</md5>
    <crc32>a8e5f43f</crc32>
    <sha1>82e515fe2ba6b7bd117e8477078441af17567193</sha1>
  </file>
  <file name="2.26441.COALPROJECT.RECORD33_archive.torrent" source="metadata">
    <btih>1355fa27b6f8d543dc8190ad930fed1022af6980</btih>
    <mtime>1405462858</mtime>
    <size>1944</size>
    <md5>c22ef290b0d1b85894a1a714fd8e1584</md5>
    <crc32>33dfe2c6</crc32>
    <sha1>9315b3f7d94aa667e238144e707a84c708d3f48b</sha1>
    <format>Archive BitTorrent</format>
  </file>
  <file name="2.26441.COALPROJECT.RECORD33_files.xml" source="original">
    <format>Metadata</format>
    <md5>6da428ead0d573b934e2a44a4ebc7738</md5>
  </file>
</files>
