<?xml version="1.0" encoding="UTF-8"?>
<metadata>
  <identifier>WARCdealer_BarrelData_rochuwd_1e1c0803-7237-4119-9407-fb8a6c42b703.2016-03-07-07-46-00-329262-_E</identifier>
  <publicdate>2016-03-07 06:46:33</publicdate>
  <title>WARCdealer_BarrelData_rochuwd_1e1c0803-7237-4119-9407-fb8a6c42b703.2016-03-07-07-46-00-329262-_E</title>
  <mediatype>data</mediatype>
  <collection>opensource</collection>
  <uploader>worldpeacehaven@gmail.com</uploader>
  <addeddate>2016-03-07 06:46:33</addeddate>
  <curation>[curator]validator@archive.org[/curator][date]20160307064722[/date][comment]checked for malware[/comment]</curation>
</metadata>
