<?xml version="1.0" encoding="UTF-8"?>
<files>
  <file name="2274.coal4" source="original">
    <format>Unknown</format>
    <mtime>1403934322</mtime>
    <size>901</size>
    <md5>8a497f4288e09407ec4d509d0ce2908c</md5>
    <crc32>404f70c9</crc32>
    <sha1>adb62d280d3b04476f8863e8872a52913d2e3470</sha1>
  </file>
  <file name="2.27455.COALPROJECT.RECORD33_meta.sqlite" source="original">
    <format>Metadata</format>
    <mtime>1403934326</mtime>
    <size>6144</size>
    <md5>650428b95322ba6f05e9987d4ca4fc9d</md5>
    <crc32>4ee5cfca</crc32>
    <sha1>66d1377ed1317e38db8ad5140cfd578d43da8a76</sha1>
  </file>
  <file name="2.27455.COALPROJECT.RECORD33_meta.xml" source="original">
    <format>Metadata</format>
    <mtime>1405462856</mtime>
    <size>503</size>
    <md5>8682337156cd2a35c8ed1acaeea7d4a6</md5>
    <crc32>5f879e07</crc32>
    <sha1>decd6acebefefafc608e935fa56fb401c4ec54ad</sha1>
  </file>
  <file name="2.27455.COALPROJECT.RECORD33_archive.torrent" source="metadata">
    <btih>dc39e9f8e6b94b263f8150050592a84eac070044</btih>
    <mtime>1405462857</mtime>
    <size>1781</size>
    <md5>dd19bce14ab9851a7eba6f669943ad55</md5>
    <crc32>8dad3e08</crc32>
    <sha1>87ef4186e30f0fa7d58aeb06ef5000e69948870d</sha1>
    <format>Archive BitTorrent</format>
  </file>
  <file name="2.27455.COALPROJECT.RECORD33_files.xml" source="original">
    <format>Metadata</format>
    <md5>3e14a7163c7214949c3d1a3262c64780</md5>
  </file>
</files>
