<?xml version="1.0" encoding="UTF-8"?>
<metadata>
  <identifier>AMJ_BarrelData_3587_c0e00db9-bfd4-4dba-845e-5d0166b0ba23.2013-11-25-03-25-12-507573-_E</identifier>
  <collection>amjbarreldata</collection>
  <description>Arcmaj3 data. Barrel 3587, c0e00db9-bfd4-4dba-845e-5d0166b0ba23</description>
  <mediatype>web</mediatype>
  <subject>Arcmaj3; WARC; snapshot; archive; Arcmaj3BarrelData</subject>
  <title>Arcmaj3 data. Barrel 3587, c0e00db9-bfd4-4dba-845e-5d0166b0ba23</title>
  <publicdate>2013-11-25 08:31:20</publicdate>
  <uploader>worldpeacehaven@gmail.com</uploader>
  <addeddate>2013-11-25 08:31:20</addeddate>
  <curation>[curator]malware@archive.org[/curator][date]20140314034837[/date][comment]checked for malware[/comment]</curation>
  <collection>data</collection>
</metadata>
