<?xml version="1.0" encoding="UTF-8"?>
<metadata>
  <identifier>WARCdealer_BarrelData_rochuwd_517c132f-ed7d-4128-94f8-4ac7f951a821.2016-03-01-19-28-32-017648-_E</identifier>
  <publicdate>2016-03-01 18:28:38</publicdate>
  <title>WARCdealer_BarrelData_rochuwd_517c132f-ed7d-4128-94f8-4ac7f951a821.2016-03-01-19-28-32-017648-_E</title>
  <mediatype>data</mediatype>
  <collection>opensource</collection>
  <uploader>worldpeacehaven@gmail.com</uploader>
  <addeddate>2016-03-01 18:28:38</addeddate>
  <curation>[curator]validator@archive.org[/curator][date]20160301182900[/date][comment]checked for malware[/comment]</curation>
</metadata>
