<?xml version="1.0" encoding="UTF-8"?>
<metadata>
  <identifier>WARCdealer_BarrelData_rochuwd_2517710e-1010-4d71-a582-11b88673f392.2016-03-07-20-33-47-547619-_E</identifier>
  <publicdate>2016-03-07 19:34:19</publicdate>
  <title>WARCdealer_BarrelData_rochuwd_2517710e-1010-4d71-a582-11b88673f392.2016-03-07-20-33-47-547619-_E</title>
  <mediatype>data</mediatype>
  <collection>opensource</collection>
  <uploader>worldpeacehaven@gmail.com</uploader>
  <addeddate>2016-03-07 19:34:19</addeddate>
  <curation>[curator]validator@archive.org[/curator][date]20160307193449[/date][comment]checked for malware[/comment]</curation>
</metadata>
