<?xml version="1.0" encoding="UTF-8"?>
<metadata>
  <identifier>AMJ_BarrelData_4209_76753d14-046e-469a-85e9-b4c608a328da.2013-11-25-23-29-52-154092-_E</identifier>
  <collection>amjbarreldata</collection>
  <description>Arcmaj3 data. Barrel 4209, 76753d14-046e-469a-85e9-b4c608a328da</description>
  <mediatype>web</mediatype>
  <subject>Arcmaj3; WARC; snapshot; archive; Arcmaj3BarrelData</subject>
  <title>Arcmaj3 data. Barrel 4209, 76753d14-046e-469a-85e9-b4c608a328da</title>
  <publicdate>2013-11-26 04:30:59</publicdate>
  <uploader>worldpeacehaven@gmail.com</uploader>
  <addeddate>2013-11-26 04:30:59</addeddate>
  <curation>[curator]malware@archive.org[/curator][date]20140314033813[/date][comment]checked for malware[/comment]</curation>
  <collection>data</collection>
</metadata>
