<?xml version="1.0" encoding="UTF-8"?>
<files>
  <file name="3.71957.COALPROJECT.RECORD33_meta.sqlite" source="original">
    <format>Metadata</format>
    <mtime>1404072868</mtime>
    <size>6144</size>
    <md5>cd592aa73020b75ac04b583f2ef3bb7b</md5>
    <crc32>9c5a0307</crc32>
    <sha1>79a3b290faf3501f46366a96b626bc6e6f31d851</sha1>
  </file>
  <file name="3719.coal4" source="original">
    <format>Unknown</format>
    <mtime>1404072863</mtime>
    <size>3205</size>
    <md5>91670503d4477296ae3be4b4fd8b2acc</md5>
    <crc32>f9bf5101</crc32>
    <sha1>3580c4603b4726827de51ef22042e4c5de126099</sha1>
  </file>
  <file name="3.71957.COALPROJECT.RECORD33_meta.xml" source="original">
    <format>Metadata</format>
    <mtime>1405462494</mtime>
    <size>503</size>
    <md5>f3e2b1da3cd98150d77d7504903de364</md5>
    <crc32>3d423775</crc32>
    <sha1>626777fa7087cd84b95751fc730537334ee5220b</sha1>
  </file>
  <file name="3.71957.COALPROJECT.RECORD33_archive.torrent" source="metadata">
    <btih>e8dea653bd221c4bf9d646eb2ec1e328cd5a9c47</btih>
    <mtime>1405462494</mtime>
    <size>1780</size>
    <md5>863482b84e9a2b40072fbe6981bdae9a</md5>
    <crc32>1ce14faa</crc32>
    <sha1>46f220973e94806c4645a3cf99f188e1b68bb885</sha1>
    <format>Archive BitTorrent</format>
  </file>
  <file name="3.71957.COALPROJECT.RECORD33_files.xml" source="original">
    <format>Metadata</format>
    <md5>2364621f77207fc5380ddf084c7639a7</md5>
  </file>
</files>
