<?xml version="1.0" encoding="UTF-8"?>
<files>
  <file name="2.23845.COALPROJECT.RECORD33_meta.sqlite" source="original">
    <format>Metadata</format>
    <mtime>1403925608</mtime>
    <size>6144</size>
    <md5>25a463bd018537d475b6fb3092884759</md5>
    <crc32>62cf03c7</crc32>
    <sha1>794dc7ebaed2897381eaaa892356d4dd2d75d9f2</sha1>
  </file>
  <file name="2238.coal4" source="original">
    <format>Unknown</format>
    <mtime>1403925604</mtime>
    <size>2137</size>
    <md5>48b459a3313fa387a4e3028513b1eefa</md5>
    <crc32>60bea9b3</crc32>
    <sha1>1c1ddd25349863657b946773c22f052e6ef8c799</sha1>
  </file>
  <file name="2.23845.COALPROJECT.RECORD33_meta.xml" source="original">
    <format>Metadata</format>
    <mtime>1472252400</mtime>
    <size>584</size>
    <md5>d87de115103215910bee57cd21db6a3d</md5>
    <crc32>ce71dd8a</crc32>
    <sha1>a8e8c7dde123000eb93aaebc0e2540b71f9fa007</sha1>
  </file>
  <file name="2.23845.COALPROJECT.RECORD33_archive.torrent" source="metadata">
    <btih>b633377aa21d081a58326f5032f277ff786cf5c9</btih>
    <mtime>1472252400</mtime>
    <size>1785</size>
    <md5>a3922dac0fff0848505aa64682d189a2</md5>
    <crc32>51f5ed19</crc32>
    <sha1>529f33f304f72ac574388cfd2f79d83b89403138</sha1>
    <format>Archive BitTorrent</format>
  </file>
  <file name="2.23845.COALPROJECT.RECORD33_files.xml" source="original">
    <format>Metadata</format>
    <md5>df5571e456cd2816c301ecac37bf1f34</md5>
  </file>
</files>
