<?xml version="1.0" encoding="UTF-8"?>
<files>
  <file name="3778.coal4" source="original">
    <format>Unknown</format>
    <mtime>1404074081</mtime>
    <size>2053</size>
    <md5>309f10cac29d10c769f627c553f9ee54</md5>
    <crc32>de859f0d</crc32>
    <sha1>0bef8c23cc787d42b21ec1f5324327805c6f8626</sha1>
  </file>
  <file name="3.77830.COALPROJECT.RECORD33_meta.sqlite" source="original">
    <format>Metadata</format>
    <mtime>1404074101</mtime>
    <size>6144</size>
    <md5>49b30b90dee7fb19fccd1e3d2ce3e5e0</md5>
    <crc32>f801192e</crc32>
    <sha1>d6bd97012fa436870ee20cf97e925be047bac634</sha1>
  </file>
  <file name="3.77830.COALPROJECT.RECORD33_meta.xml" source="original">
    <format>Metadata</format>
    <mtime>1405462479</mtime>
    <size>503</size>
    <md5>a49fc9ac4cdf251d186065238b63b7d7</md5>
    <crc32>5be1455f</crc32>
    <sha1>816eb098a42701fc314765f3e8db78d62a4401e9</sha1>
  </file>
  <file name="3.77830.COALPROJECT.RECORD33_archive.torrent" source="metadata">
    <btih>121fffd7c37bbc5ec1dfa4290e373f545c69fee6</btih>
    <mtime>1405462480</mtime>
    <size>1752</size>
    <md5>27f6124c3b8db870f8a163b1705fc848</md5>
    <crc32>2f5d3b81</crc32>
    <sha1>121a3eb4d118dc83a8339aa7aacfd74c024a2e2d</sha1>
    <format>Archive BitTorrent</format>
  </file>
  <file name="3.77830.COALPROJECT.RECORD33_files.xml" source="original">
    <format>Metadata</format>
    <md5>d84261fd0d22c518595254bb6b2fae05</md5>
  </file>
</files>
