<?xml version="1.0" encoding="UTF-8"?>
<metadata>
  <identifier>AMJ_BarrelData_5012_7214c9a3-a527-4271-a313-505c657830fd.2013-11-26-04-17-43-715512-_E</identifier>
  <collection>amjbarreldata</collection>
  <description>Arcmaj3 data. Barrel 5012, 7214c9a3-a527-4271-a313-505c657830fd</description>
  <mediatype>web</mediatype>
  <subject>Arcmaj3; WARC; snapshot; archive; Arcmaj3BarrelData</subject>
  <title>Arcmaj3 data. Barrel 5012, 7214c9a3-a527-4271-a313-505c657830fd</title>
  <publicdate>2013-11-26 09:17:56</publicdate>
  <uploader>worldpeacehaven@gmail.com</uploader>
  <addeddate>2013-11-26 09:17:56</addeddate>
  <curation>[curator]malware@archive.org[/curator][date]20140314032835[/date][comment]checked for malware[/comment]</curation>
  <collection>data</collection>
</metadata>
