<?xml version="1.0" encoding="UTF-8"?>
<metadata>
  <identifier>AMJ_BarrelData_6731_e6a8d277-e00a-4fe0-8877-ebd8a4f08f6a.2013-12-17-21-02-25-690765-_E</identifier>
  <collection>amjbarreldata</collection>
  <description>Arcmaj3 data. Barrel 6731, e6a8d277-e00a-4fe0-8877-ebd8a4f08f6a</description>
  <mediatype>web</mediatype>
  <subject>Arcmaj3; WARC; snapshot; archive; Arcmaj3BarrelData</subject>
  <title>Arcmaj3 data. Barrel 6731, e6a8d277-e00a-4fe0-8877-ebd8a4f08f6a</title>
  <publicdate>2013-12-18 02:07:04</publicdate>
  <uploader>worldpeacehaven@gmail.com</uploader>
  <addeddate>2013-12-18 02:07:04</addeddate>
  <curation>[curator]malware@archive.org[/curator][date]20140313144307[/date][comment]checked for malware[/comment]</curation>
  <collection>data</collection>
</metadata>
