<?xml version="1.0" encoding="UTF-8"?>
<files>
  <file name="Buck Bundy Hosts Beethoven -   Part 1 (1993)-FAEdfbLPyqQ.webm" source="original">
    <mtime>1429830274</mtime>
    <size>473</size>
    <md5>def5109bfeae34e96b6f6d48be0229be</md5>
    <crc32>5899c85f</crc32>
    <sha1>c75cc5840c35167dded4d11e11a9bf308d548fae</sha1>
    <format>WebM</format>
    <length>0</length>
    <height>0</height>
    <width>0</width>
  </file>
  <file name="Buck Bundy Hosts Beethoven -   Part 1 (1993)-FAEdfbLPyqQ.webm.description" source="original">
    <mtime>1429830280</mtime>
    <size>73</size>
    <md5>2bbb7536458ff55d9e6bb02a36ae07e4</md5>
    <crc32>c7cf557c</crc32>
    <sha1>d73789759f68db44487407cc3feaab5e32dd66e5</sha1>
    <format>Unknown</format>
  </file>
  <file name="Buck Bundy Hosts Beethoven -   Part 1 (1993)-FAEdfbLPyqQ.f243.webm" source="original">
    <mtime>1429830270</mtime>
    <size>1562297</size>
    <md5>9fac8652b5cbe9c9a9b47d8a4acd5978</md5>
    <crc32>0a8ca26f</crc32>
    <sha1>e77b20d7f8da41b266771013d9abf6a8a6b55449</sha1>
    <format>WebM</format>
    <length>36.67</length>
    <height>360</height>
    <width>476</width>
  </file>
  <file name="Buck Bundy Hosts Beethoven -   Part 1 (1993)-FAEdfbLPyqQ.jpg" source="original">
    <mtime>1429830272</mtime>
    <size>26345</size>
    <md5>d714a8e074eb2d1ca52ff5313d4b72b3</md5>
    <crc32>b0e8e66d</crc32>
    <sha1>ef08c43a8a50ca75658c508852ca031c11a7f94c</sha1>
    <format>JPEG</format>
    <rotation>0</rotation>
  </file>
  <file name="Buck Bundy Hosts Beethoven -   Part 1 (1993)-FAEdfbLPyqQ.f141.m4a" source="original">
    <mtime>1429830267</mtime>
    <size>1172553</size>
    <md5>a5b700c0ef35447dabcd53b711ba761a</md5>
    <crc32>f8193736</crc32>
    <sha1>444726fbf7657448ec26dafdebe00ed615863645</sha1>
    <format>Apple Lossless Audio</format>
  </file>
  <file name="BuckBundyHostsBeethovenPart11993FAEdfbLPyqQ_meta.sqlite" source="original">
    <mtime>1429830290</mtime>
    <size>15360</size>
    <md5>a2741233f21feb53cd63ae521ce22243</md5>
    <crc32>2feef942</crc32>
    <sha1>8295febf8c5780532f1569ba46ba3d33a569dfb9</sha1>
    <format>Metadata</format>
  </file>
  <file name="Buck Bundy Hosts Beethoven -   Part 1 (1993)-FAEdfbLPyqQ.webm.annotations.xml" source="original">
    <mtime>1429830277</mtime>
    <size>87</size>
    <md5>8b5e6989c77b2dd00f4d947d4833f697</md5>
    <crc32>ebde1c92</crc32>
    <sha1>324156a033670198eaba2922ca07ccae0d90d166</sha1>
    <format>Metadata</format>
  </file>
  <file name="Buck Bundy Hosts Beethoven -   Part 1 (1993)-FAEdfbLPyqQ.info.json" source="original">
    <mtime>1429830257</mtime>
    <size>31148</size>
    <md5>14b9543a6fcb770efcb5d8566e777e21</md5>
    <crc32>b03baf45</crc32>
    <sha1>c0660ea78f7af41b29898f11db82c048fad26ee3</sha1>
    <format>JSON</format>
  </file>
  <file name="BuckBundyHostsBeethovenPart11993FAEdfbLPyqQ_meta.xml" source="original">
    <mtime>1429830607</mtime>
    <size>999</size>
    <format>Metadata</format>
    <md5>8ad0f76b90cd5d2ace5fd02e15509249</md5>
    <crc32>14a10f9b</crc32>
    <sha1>df08768fc46e2a2a74a561b91ab7b32bdb1ada79</sha1>
  </file>
  <file name="Buck Bundy Hosts Beethoven -   Part 1 (1993)-FAEdfbLPyqQ.f243.ogv" source="derivative">
    <format>Ogg Video</format>
    <original>Buck Bundy Hosts Beethoven -   Part 1 (1993)-FAEdfbLPyqQ.f243.webm</original>
    <mtime>1429830907</mtime>
    <size>2367500</size>
    <md5>0d9fa7557c8df010d8bbd99d43698cd0</md5>
    <crc32>d4f3d404</crc32>
    <sha1>90ac38f2cc436b7c289cdafde4d43a849b6f58f9</sha1>
    <length>36.7</length>
    <height>300</height>
    <width>397</width>
  </file>
  <file name="Buck Bundy Hosts Beethoven -   Part 1 (1993)-FAEdfbLPyqQ.f141_esslow.json.gz" source="derivative">
    <format>Essentia Low GZ</format>
    <original>Buck Bundy Hosts Beethoven -   Part 1 (1993)-FAEdfbLPyqQ.f141.m4a</original>
    <mtime>1429830920</mtime>
    <size>21282</size>
    <md5>21eaf5f0058adc38ec5f594439fc3363</md5>
    <crc32>a5b75884</crc32>
    <sha1>31571260a4dde5013bc0335808efeb1860515620</sha1>
  </file>
  <file name="Buck Bundy Hosts Beethoven -   Part 1 (1993)-FAEdfbLPyqQ.f141.ogg" source="derivative">
    <format>Ogg Vorbis</format>
    <original>Buck Bundy Hosts Beethoven -   Part 1 (1993)-FAEdfbLPyqQ.f141.m4a</original>
    <mtime>1429830670</mtime>
    <size>365397</size>
    <md5>48ae52b07436ad05b1e194fd87603e59</md5>
    <crc32>4740e332</crc32>
    <sha1>3ce72361d12a2e9f532ed959003cefbc0f0183b8</sha1>
    <length>36.76</length>
    <height>0</height>
    <width>0</width>
  </file>
  <file name="Buck Bundy Hosts Beethoven -   Part 1 (1993)-FAEdfbLPyqQ.f243.gif" source="derivative">
    <format>Animated GIF</format>
    <original>Buck Bundy Hosts Beethoven -   Part 1 (1993)-FAEdfbLPyqQ.f243.webm</original>
    <mtime>1429830637</mtime>
    <size>114403</size>
    <md5>958e75996becc942e5e687f47c3fc420</md5>
    <crc32>3d6faf5f</crc32>
    <sha1>e8093ce6ac836330d1bc40887343949549b042ec</sha1>
  </file>
  <file name="Buck Bundy Hosts Beethoven -   Part 1 (1993)-FAEdfbLPyqQ.f141.afpk" source="derivative">
    <format>Columbia Peaks</format>
    <original>Buck Bundy Hosts Beethoven -   Part 1 (1993)-FAEdfbLPyqQ.f141.m4a</original>
    <mtime>1429830926</mtime>
    <size>7256</size>
    <md5>9415e12583e6c09148d70bb6617a6e28</md5>
    <crc32>abc9c5e7</crc32>
    <sha1>8c15a6d75f0cac0ce428a412dfc30033ad8a4bcc</sha1>
  </file>
  <file name="BuckBundyHostsBeethovenPart11993FAEdfbLPyqQ.thumbs/Buck Bundy Hosts Beethoven -   Part 1 (1993)-FAEdfbLPyqQ.f243_000012.jpg" source="derivative">
    <format>Thumbnail</format>
    <original>Buck Bundy Hosts Beethoven -   Part 1 (1993)-FAEdfbLPyqQ.f243.webm</original>
    <mtime>1429830648</mtime>
    <size>7256</size>
    <md5>bb0d4bc87afb0065b01f5584003135da</md5>
    <crc32>4f263bd9</crc32>
    <sha1>c68e950d3c24d56861ef0a3c69ac4ad76685fc5d</sha1>
  </file>
  <file name="BuckBundyHostsBeethovenPart11993FAEdfbLPyqQ.thumbs/Buck Bundy Hosts Beethoven -   Part 1 (1993)-FAEdfbLPyqQ.f243_000032.jpg" source="derivative">
    <format>Thumbnail</format>
    <original>Buck Bundy Hosts Beethoven -   Part 1 (1993)-FAEdfbLPyqQ.f243.webm</original>
    <mtime>1429830660</mtime>
    <size>1880</size>
    <md5>139d980f273e4817df43837011265442</md5>
    <crc32>9f480cb6</crc32>
    <sha1>fd24c9b47ad6c75d4e44dd8584cc44e68cd078e2</sha1>
  </file>
  <file name="BuckBundyHostsBeethovenPart11993FAEdfbLPyqQ.thumbs/Buck Bundy Hosts Beethoven -   Part 1 (1993)-FAEdfbLPyqQ.f243_000007.jpg" source="derivative">
    <format>Thumbnail</format>
    <original>Buck Bundy Hosts Beethoven -   Part 1 (1993)-FAEdfbLPyqQ.f243.webm</original>
    <mtime>1429830645</mtime>
    <size>12024</size>
    <md5>455d86d124afd392704de383bb693db7</md5>
    <crc32>7b02262c</crc32>
    <sha1>0fe033ae91946377b3a4ba04df951d48c2181a14</sha1>
  </file>
  <file name="BuckBundyHostsBeethovenPart11993FAEdfbLPyqQ.thumbs/Buck Bundy Hosts Beethoven -   Part 1 (1993)-FAEdfbLPyqQ.f243_000017.jpg" source="derivative">
    <format>Thumbnail</format>
    <original>Buck Bundy Hosts Beethoven -   Part 1 (1993)-FAEdfbLPyqQ.f243.webm</original>
    <mtime>1429830651</mtime>
    <size>4109</size>
    <md5>e5fb400a1dd4269f07d5a30fb2fa93e1</md5>
    <crc32>9f3a128a</crc32>
    <sha1>b4d0acbdd9581d75811d127a5a1bea3114a42a11</sha1>
  </file>
  <file name="BuckBundyHostsBeethovenPart11993FAEdfbLPyqQ.thumbs/Buck Bundy Hosts Beethoven -   Part 1 (1993)-FAEdfbLPyqQ.f243_000027.jpg" source="derivative">
    <format>Thumbnail</format>
    <original>Buck Bundy Hosts Beethoven -   Part 1 (1993)-FAEdfbLPyqQ.f243.webm</original>
    <mtime>1429830657</mtime>
    <size>2158</size>
    <md5>f5d18cacb9a406bdc1965577a66555ee</md5>
    <crc32>8670e3c5</crc32>
    <sha1>08f8ea12dedc486fb2bd9206b74b67905ebd7a36</sha1>
  </file>
  <file name="BuckBundyHostsBeethovenPart11993FAEdfbLPyqQ.thumbs/Buck Bundy Hosts Beethoven -   Part 1 (1993)-FAEdfbLPyqQ.f243_000001.jpg" source="derivative">
    <format>Thumbnail</format>
    <original>Buck Bundy Hosts Beethoven -   Part 1 (1993)-FAEdfbLPyqQ.f243.webm</original>
    <mtime>1429830643</mtime>
    <size>4290</size>
    <md5>d07fcfaf43f971ce32dad32dc9e52d94</md5>
    <crc32>65c26dc7</crc32>
    <sha1>db20eb5f61e89076dff4196633ba4079df40a3cc</sha1>
  </file>
  <file name="BuckBundyHostsBeethovenPart11993FAEdfbLPyqQ.thumbs/Buck Bundy Hosts Beethoven -   Part 1 (1993)-FAEdfbLPyqQ.f243_000022.jpg" source="derivative">
    <format>Thumbnail</format>
    <original>Buck Bundy Hosts Beethoven -   Part 1 (1993)-FAEdfbLPyqQ.f243.webm</original>
    <mtime>1429830654</mtime>
    <size>2552</size>
    <md5>885b0fa95230b10ac3718511a6b7a31b</md5>
    <crc32>fbfd22bb</crc32>
    <sha1>95910744086025ac7b8ae4d5d96eef06eb4c8cdc</sha1>
  </file>
  <file name="Buck Bundy Hosts Beethoven -   Part 1 (1993)-FAEdfbLPyqQ.f141.mp3" source="derivative">
    <bitrate>149</bitrate>
    <length>00:36</length>
    <format>VBR MP3</format>
    <original>Buck Bundy Hosts Beethoven -   Part 1 (1993)-FAEdfbLPyqQ.f141.m4a</original>
    <mtime>1429830666</mtime>
    <size>766464</size>
    <md5>21488cffc49bc9908afe7aac05ff5c61</md5>
    <crc32>011728fb</crc32>
    <sha1>97c31fc5fb8af7300e3e2035a3cb9fe4025ab8bd</sha1>
    <height>0</height>
    <width>0</width>
  </file>
  <file name="Buck Bundy Hosts Beethoven -   Part 1 (1993)-FAEdfbLPyqQ.f141_esshigh.json.gz" source="derivative">
    <format>Essentia High GZ</format>
    <original>Buck Bundy Hosts Beethoven -   Part 1 (1993)-FAEdfbLPyqQ.f141_esslow.json.gz</original>
    <mtime>1429830946</mtime>
    <size>1897</size>
    <md5>325a21e0c9c408fb8084fccb85823bb0</md5>
    <crc32>3a888c29</crc32>
    <sha1>246d619655f4762231c48bb5bdb8e9ac42ba86c9</sha1>
  </file>
  <file name="Buck Bundy Hosts Beethoven -   Part 1 (1993)-FAEdfbLPyqQ.f243.mp4" source="derivative">
    <format>h.264</format>
    <original>Buck Bundy Hosts Beethoven -   Part 1 (1993)-FAEdfbLPyqQ.f243.webm</original>
    <mtime>1429830825</mtime>
    <size>3150587</size>
    <md5>678eb4733744270c8641f35ca24dde88</md5>
    <crc32>651a675c</crc32>
    <sha1>2581a90e05f1713f80781a90678d457fbda93367</sha1>
    <length>36.7</length>
    <height>480</height>
    <width>635</width>
  </file>
  <file name="Buck Bundy Hosts Beethoven -   Part 1 (1993)-FAEdfbLPyqQ.f141.png" source="derivative">
    <format>PNG</format>
    <original>Buck Bundy Hosts Beethoven -   Part 1 (1993)-FAEdfbLPyqQ.f141.m4a</original>
    <mtime>1429830913</mtime>
    <size>12892</size>
    <md5>98da77896ea7b5c39a4134c1f7e39dd0</md5>
    <crc32>8ea8d47f</crc32>
    <sha1>9a4a7b242de0f3344dfde51d2ba46a89736d21f7</sha1>
  </file>
  <file name="Buck Bundy Hosts Beethoven -   Part 1 (1993)-FAEdfbLPyqQ_thumb.jpg" source="derivative">
    <format>JPEG Thumb</format>
    <original>Buck Bundy Hosts Beethoven -   Part 1 (1993)-FAEdfbLPyqQ.jpg</original>
    <mtime>1429830910</mtime>
    <size>6735</size>
    <md5>7d38e8495f8438795abb6a3d09ca55ce</md5>
    <crc32>906deecb</crc32>
    <sha1>48b2264b00ff999f82bdb989057f86d66a886de4</sha1>
  </file>
  <file name="BuckBundyHostsBeethovenPart11993FAEdfbLPyqQ_archive.torrent" source="metadata">
    <btih>10b0bc0516cae02fce934b76127ce72f81ef2ffb</btih>
    <mtime>1429830957</mtime>
    <size>5880</size>
    <md5>21ac481d224bbd28d7fa76323858f987</md5>
    <crc32>1feb948e</crc32>
    <sha1>c8a2c924e21c89ba95221263f0e1c68fe5753bca</sha1>
    <format>Archive BitTorrent</format>
  </file>
  <file name="BuckBundyHostsBeethovenPart11993FAEdfbLPyqQ_files.xml" source="original">
    <format>Metadata</format>
    <md5>d0d512d0f0df85de02feb362259aa7d3</md5>
  </file>
</files>
