<?xml version="1.0" encoding="UTF-8"?>
<metadata>
  <identifier>AMJ_BarrelData_4017_9ff98c12-b1fd-45b9-8f53-557572053b3d.2013-11-25-12-48-05-171909-_E</identifier>
  <collection>amjbarreldata</collection>
  <description>Arcmaj3 data. Barrel 4017, 9ff98c12-b1fd-45b9-8f53-557572053b3d</description>
  <mediatype>web</mediatype>
  <subject>Arcmaj3; WARC; snapshot; archive; Arcmaj3BarrelData</subject>
  <title>Arcmaj3 data. Barrel 4017, 9ff98c12-b1fd-45b9-8f53-557572053b3d</title>
  <publicdate>2013-11-25 17:52:39</publicdate>
  <uploader>worldpeacehaven@gmail.com</uploader>
  <addeddate>2013-11-25 17:52:39</addeddate>
  <curation>[curator]malware@archive.org[/curator][date]20140314034302[/date][comment]checked for malware[/comment]</curation>
  <collection>data</collection>
</metadata>
